{"sourceFile": [{
      "name": "",
      "directive": [
        {
          "functionName": "sha256_verify",
          "label": "",
          "functionLabel": "",
          "id": "1",
          "sourceFile": "\/home\/dimitra\/Coyote-playground\/replacingLastPacket\/sum_of_all_input_data_plus_verify\/vitis2\/shav2\/solution1\/csynth.tcl",
          "sourceLine": "19",
          "pragma": {
            "name": "TOP",
            "option": [{
                "name": "name",
                "value": "sha256_verify"
              }]
          }
        },
        {
          "functionName": "sha256_verify",
          "label": "",
          "functionLabel": "",
          "id": "2",
          "sourceFile": "\/home\/dimitra\/Coyote-playground\/replacingLastPacket\/sum_of_all_input_data_plus_verify\/vitis2\/shav2\/solution1\/csynth.tcl",
          "sourceLine": "19",
          "pragma": {
            "name": "TOP",
            "option": [{
                "name": "name",
                "value": "sha256_verify"
              }]
          }
        },
        {
          "functionName": "sha256_verify",
          "label": "",
          "functionLabel": "",
          "id": "3",
          "sourceFile": "\/home\/dimitra\/Coyote-playground\/replacingLastPacket\/sum_of_all_input_data_plus_verify\/vitis2\/shav2\/solution1\/csynth.tcl",
          "sourceLine": "19",
          "pragma": {
            "name": "TOP",
            "option": [{
                "name": "name",
                "value": "sha256_verify"
              }]
          }
        }
      ]
    }]}
